TADA_T2/TADA.py
TADA_T2/__init__.py
TADA_T2/_version.py
TADA_T2/py.typed
TADA_T2/backend/features.py
TADA_T2/backend/model.py
TADA_T2/backend/predictor.py
TADA_T2/backend/utils.py
TADA_T2/data/README.md
TADA_T2/data/scaler_metric.arr
TADA_T2/data/scaler_metric.npy
TADA_T2/data/tada.14-0.02.hdf5
TADA_T2/data/testing.fasta
TADA_T2/tests/__init__.py
TADA_T2/tests/test_TADA_T2.py
TADA_T2/tests/test_predictor_is_correct.py
TADA_T2-0.14.0.dist-info/LICENSE
TADA_T2-0.14.0.dist-info/METADATA
TADA_T2-0.14.0.dist-info/WHEEL
TADA_T2-0.14.0.dist-info/top_level.txt
TADA_T2-0.14.0.dist-info/RECORD
