Metadata-Version: 2.1
Name: TADA_T2
Version: 0.14.0
Summary: A Tensorflow2 compatible version of the TADA transcriptional activation domain predictor.
Author-email: Ryan Emenecker Holehouse Lab WUSM <remenecker@wustl.edu>
License: MIT
Classifier: License :: OSI Approved :: MIT License
Classifier: Programming Language :: Python :: 3
Requires-Python: >=3.8
License-File: LICENSE
Requires-Dist: alphaPredict >=1.2
Requires-Dist: Tensorflow >=2.10.0
Requires-Dist: localcider
Requires-Dist: numpy
Requires-Dist: protfasta
Provides-Extra: test
Requires-Dist: pytest >=6.1.2 ; extra == 'test'
